{ "compressionlevel":-1,
 "height":38,
 "infinite":false,
 "layers":[
        {
         "compression":"zlib",
         "data":"eJztl1sLwyAMhW375Ngeetn\/\/6szsEAIyhpzttCuBw4iXj6oMbFLSmkJ8lQ8Ft9AHj6MZ9Uf30YpG+ej+Vah+VMw37rXxT8un2JtFf052fOPh0\/r5H3XuWVvvvLwvcrBfN6HvoM+m1XNm9UYkt86OyldRxB8rn89QvC98R\/JH4L51lpfk+f+I4SKY488+T+ST2d3L34YWhblMsphnvtPZ7cVPw2tXPuN969VF\/+4fIph7x1kfqvu65ovhchdzJf1v\/Wmq+V7FN+z\/l\/4tVj7Jb827wz8nv8mlKmG9vw3oUzsF4cRDOw=",
         "encoding":"base64",
         "height":38,
         "id":1,
         "name":"wall",
         "opacity":1,
         "type":"tilelayer",
         "visible":true,
         "width":32,
         "x":0,
         "y":0
        }, 
        {
         "compression":"zlib",
         "data":"eJztk8sKgCAQRd27d9sLql3+\/9dVoDCIIvOgwfTC2VQzZ5rSmBEnxJsLQcxOJA3GDf0HkeVhDWyM9z+J5ELxTwhmgAM9ON8f\/j+1wFk0\/LV87ZeYndPDBiT82LNvmaR+zDmQ8Nf2VnuudT+nz\/D37ZdA28\/Zo9TcHD82pdoW\/V6A4W\/XHyPhT1O6n6vV8vvCNYqfU9+LX3v\/f\/b3nBsCN19q",
         "encoding":"base64",
         "height":38,
         "id":2,
         "name":"floor",
         "opacity":1,
         "type":"tilelayer",
         "visible":true,
         "width":32,
         "x":0,
         "y":0
        }, 
        {
         "compression":"zlib",
         "data":"eJztz7EJACAMBMCsofsPapNCLEQkCMIdfJMin0QAt1qmctcuq56p0A+y3jPPX\/RX\/nvSv5sDAADwjwHCfwUF",
         "encoding":"base64",
         "height":38,
         "id":3,
         "name":"water",
         "opacity":1,
         "type":"tilelayer",
         "visible":true,
         "width":32,
         "x":0,
         "y":0
        }, 
        {
         "compression":"zlib",
         "data":"eJzt1LsKgDAQRNHttNNOW2MVrfT\/Py67GCGIIPhgEe6BaXcYAhHBXVEz5cwO\/YMm5IwO\/ba\/0tTit7\/RtPJsf\/mO5XvatkW2fVHON+79X7Db4eI+\/b79naZ\/qe\/4n9jtNd\/3\/msAAAAA4O8Sxu8G5w==",
         "encoding":"base64",
         "height":38,
         "id":4,
         "name":"bridg",
         "opacity":1,
         "type":"tilelayer",
         "visible":true,
         "width":32,
         "x":0,
         "y":0
        }, 
        {
         "compression":"zlib",
         "data":"eJzt1bENACAMA8FMwATQQQf7r4cLZsBE\/Elfu3QEsqmqGfe7Gsb9qZZxHwCA2\/j+vN9fTr\/uAwDwig1zRQHv",
         "encoding":"base64",
         "height":38,
         "id":5,
         "name":"stair",
         "opacity":1,
         "type":"tilelayer",
         "visible":true,
         "width":32,
         "x":0,
         "y":0
        }, 
        {
         "compression":"zlib",
         "data":"eJztzbcRgDAQRNFrC+89ZNj+G2EL0EgEnALYP\/PiL8LYu00wWyzK\/xU2i\/3j\/wNOi0v5z9gfCyB0iBT\/GeQOBf9qNdA6dIp\/xphIDIlB6ulfQmVQ888\/\/5\/\/9zAYjJ7+7Hk3waAqkQ==",
         "encoding":"base64",
         "height":38,
         "id":6,
         "name":"carpet",
         "opacity":1,
         "type":"tilelayer",
         "visible":true,
         "width":32,
         "x":0,
         "y":0
        }, 
        {
         "compression":"zlib",
         "data":"eJzt1dsKgCAMBmBftLLzAXr\/2y4iEHEwdbpJ+0AQsX4Z4oz5px5YP53hmgIjx5r5PbWb+wANmoF5LRcwxxgoD5JgY84vza8v9N6kwPzLry\/leyPt7fpQ1jiF1LqEdMz5C3O+al9MDyvR72J6mLR+Z5nzd+Z8VY4F1kfEHgrQ3ToQe5SqwTLn6\/1\/PWWvD\/M=",
         "encoding":"base64",
         "height":38,
         "id":7,
         "name":"plants",
         "opacity":1,
         "type":"tilelayer",
         "visible":true,
         "width":32,
         "x":0,
         "y":0
        }, 
        {
         "compression":"zlib",
         "data":"eJztyUENADAIBEH8S6MVBQKKANKZZD93EQAAsEt2p7vD99oBgH8VgaAD+A==",
         "encoding":"base64",
         "height":38,
         "id":8,
         "name":"furniture under",
         "opacity":1,
         "type":"tilelayer",
         "visible":true,
         "width":32,
         "x":0,
         "y":0
        }, 
        {
         "compression":"zlib",
         "data":"eJztziESADAIwDAE4\/9PBj+DwyR39Y0AAAA2cnrL6ugRAPg136sAPQ==",
         "encoding":"base64",
         "height":38,
         "id":9,
         "name":"wall 2",
         "opacity":1,
         "type":"tilelayer",
         "visible":true,
         "width":32,
         "x":0,
         "y":0
        }, 
        {
         "compression":"zlib",
         "data":"eJztzaERgDAAxdDuCzUF02IAA92abPEFeXfRKUVJC61UQ\/9GG+2hf6dBR+h\/0kV36P\/QSzP0lyRJkiTpDz6HGwcn",
         "encoding":"base64",
         "height":38,
         "id":10,
         "name":"tree 3",
         "opacity":1,
         "type":"tilelayer",
         "visible":true,
         "width":32,
         "x":0,
         "y":0
        }, 
        {
         "compression":"zlib",
         "data":"eJztzTkKgFAQBNE5sZqouOKK66Gt1ED4gTgg\/aCSTtrMrKCSKrt72t\/WUU9D4P62hVbaAnf5j4hiSpz+U8ood\/qvqaHW6X+kiWan\/50OOp3+RURERERE5BsXZyAQZg==",
         "encoding":"base64",
         "height":38,
         "id":11,
         "name":"tree 1",
         "opacity":1,
         "type":"tilelayer",
         "visible":true,
         "width":32,
         "x":0,
         "y":0
        }, 
        {
         "compression":"zlib",
         "data":"eJztzaERgDAAxdDuCzUF02IAA92abPEFeXfRKUWSMhZaqYb+jTbaQ\/9Og47Q\/6SL7tD\/oZdm6C9JkiTpPz4T4Acn",
         "encoding":"base64",
         "height":38,
         "id":12,
         "name":"tree 2",
         "opacity":1,
         "type":"tilelayer",
         "visible":true,
         "width":32,
         "x":0,
         "y":0
        }, 
        {
         "compression":"zlib",
         "data":"eJztlNcKwkAQRfeL8qLfacOOJSoW1Giw9wLWB\/\/JK0xAZCOCmaBhDhzuzu6w8zZKBY8FXEKDauNNb1BZwbVL+sEBHl2SmwsswbJGE+58mN+DfY028\/wtZQiGXZKTM\/P\/v8wNRmCU6hiMP707b4++hAfzNpq7NMzQOQtzsKJ5y3sw\/+TBH\/9OEqY+7OXYvQVYpHOV0tl9JtU1OFd8u7dO2aZswCZsUd2Be6bZXWjReUDp7F6b6iG8Kp69O4Ljl7sJnMIZwzxBEARBEAThO+58Yz2Y",
         "encoding":"base64",
         "height":38,
         "id":13,
         "name":"furniture 1",
         "opacity":1,
         "type":"tilelayer",
         "visible":true,
         "width":32,
         "x":0,
         "y":0
        }, 
        {
         "compression":"zlib",
         "data":"eJztlcdLBDEUxieoB3vB3ttFLxZwdhG96P+pXr1YrnoQ9OBNF9beFfVguyh21G\/YNxCySaaYcRecD35M8k32vQnvJWtZsaLWKljzsa6dWVYH6GSZeSvL9l0vll4pem7Qc9Nw\/N4c16E\/ovx1mrhFf7DnNk2O8rj3Y4XUio81xSyDo2pJr5XAK5D4CR+x1zXv+P8Hd9zEstc0w2sBNR7nwL3zUtpV5pSUeGHv2y7srZt5e65GgE3j2ZA5eY0hzxAYpnyDNB\/n8pcqvmXxF3kLKeYEngmQpLlN88mI776yHN+ttZQ\/aP1NS6y32A9RqUdRb7EfRO2AXbAH9sGBj1zXwnwUsfsC7m8LbIMTcArOwDm4oPeH4IjjmPvtgyTeQJ7VXzz\/Qet\/A24lYy\/ZTH7+VfXPtS4Vftj9B9WdgRiP4InG75zvjJfAsuDzSiv8IPv\/AJ++vjT\/ZKr+U2AazHBeBXq+ElRpet9E\/R3NgXmwwHn1yNsAGin\/K3gDz+CF1lwp4kXS\/\/gOBr4w\/Cbr3kTcf6wfTTBV5A==",
         "encoding":"base64",
         "height":38,
         "id":14,
         "name":"furniture top",
         "opacity":1,
         "type":"tilelayer",
         "visible":true,
         "width":32,
         "x":0,
         "y":0
        }, 
        {
         "compression":"zlib",
         "data":"eJxjYBg5YAIQTxxA+2cA8cwBtH8UjIJRMApGASpQZYRgEFBDYiMDdSxi1ALajBAMAjpIbGSgS0P7RwECmAKxBjCs9aDhbQmkLRgQfHoAY0b8\/FFAO6AHjW9LaJjD4t4EKQ4u0sDer0hsQvEfS6SZz4H4BRC\/JEKtBZFmgkAKkereA\/EHIP5IgtkDDUBxDSsDQAAULiZQMXqB0fxPGBCbB2gFiM0Do4A4AGp3\/QXSTAOU1nVG89iIBABdXBMh",
         "encoding":"base64",
         "height":38,
         "id":15,
         "name":"furniture top 2",
         "opacity":1,
         "type":"tilelayer",
         "visible":true,
         "width":32,
         "x":0,
         "y":0
        }, 
        {
         "compression":"zlib",
         "data":"eJztlGsOhDAIhN3bef8T+WsTUxmYAVo1uyRNfJT5oIxu2z86Y\/9cl7Uneva9t\/Yijrqqeue8UYc5owofaUVsZR\/Lexo\/c\/4sn9FSvdfN74o38TvqWPXfYOuN9nn\/I\/ZdlT9eK3xPT+l\/5DOaiKPMTeUzHlKeVfpn67JyUW8RD83f6sfS716Iv3Khs\/PmxMyI9TliedrZQPmV\/jv4FpPxjaej8NX+Z\/g\/4y3l27LyZ\/Kz\/Wc8EL2z9nrh+YTlo5pX8NX5ezrRDO6af5Sv9M96ZGb9DB9Fpv8oP\/KKmq\/o\/VIchZOg1Q==",
         "encoding":"base64",
         "height":38,
         "id":16,
         "name":"walk area",
         "opacity":1,
         "type":"tilelayer",
         "visible":false,
         "width":32,
         "x":0,
         "y":0
        }],
 "nextlayerid":17,
 "nextobjectid":1,
 "orientation":"orthogonal",
 "renderorder":"right-down",
 "tiledversion":"1.6.0",
 "tileheight":32,
 "tilesets":[
        {
         "columns":8,
         "firstgid":1,
         "image":"tiles/tile_1.png",
         "imageheight":224,
         "imagewidth":256,
         "margin":0,
         "name":"tile_1",
         "spacing":0,
         "tilecount":56,
         "tileheight":32,
         "tilewidth":32
        }, 
        {
         "columns":6,
         "firstgid":57,
         "image":"tiles/tile_carpet.jpg",
         "imageheight":192,
         "imagewidth":192,
         "margin":0,
         "name":"tile_carpet",
         "spacing":0,
         "tilecount":36,
         "tileheight":32,
         "tilewidth":32
        }, 
        {
         "columns":7,
         "firstgid":93,
         "image":"tiles/plants.png",
         "imageheight":224,
         "imagewidth":224,
         "margin":0,
         "name":"plants",
         "spacing":0,
         "tilecount":49,
         "tileheight":32,
         "tilewidth":32
        }, 
        {
         "columns":8,
         "firstgid":142,
         "image":"tiles/furniture_1.png",
         "imageheight":288,
         "imagewidth":256,
         "margin":0,
         "name":"furniture_1",
         "spacing":0,
         "tilecount":72,
         "tileheight":32,
         "tilewidth":32
        }, 
        {
         "columns":8,
         "firstgid":214,
         "image":"tiles/furniture-2.png",
         "imageheight":288,
         "imagewidth":256,
         "margin":0,
         "name":"furniture-2",
         "spacing":0,
         "tilecount":72,
         "tileheight":32,
         "tilewidth":32
        }, 
        {
         "columns":6,
         "firstgid":286,
         "image":"tiles/furniture_3.png",
         "imageheight":224,
         "imagewidth":192,
         "margin":0,
         "name":"furniture_3",
         "spacing":0,
         "tilecount":42,
         "tileheight":32,
         "tilewidth":32
        }, 
        {
         "columns":1,
         "firstgid":328,
         "image":"tiles/walk-area.png",
         "imageheight":32,
         "imagewidth":32,
         "margin":0,
         "name":"walk-area",
         "spacing":0,
         "tilecount":1,
         "tileheight":32,
         "tilewidth":32
        }],
 "tilewidth":32,
 "type":"map",
 "version":"1.6",
 "width":32
}